lightsearch-0.1.0.dist-info/METADATA
lightsearch-0.1.0.dist-info/WHEEL
lightsearch/py.typed
lightsearch/lib.pyi
lightsearch/__init__.py
lightsearch/lib.cpython-312-x86_64-linux-gnu.so
lightsearch-0.1.0.dist-info/RECORD
